openregister_client/__init__.py
openregister_client/fields.py
openregister_client/registers.py
openregister_client/util.py
openregister_client/django_compat/__init__.py
openregister_client/django_compat/fields.py
openregister_client/django_compat/model_factory.py
openregister_client-0.4.dist-info/LICENSE.txt
openregister_client-0.4.dist-info/METADATA
openregister_client-0.4.dist-info/WHEEL
openregister_client-0.4.dist-info/top_level.txt
openregister_client-0.4.dist-info/RECORD
