Metadata-Version: 2.1
Name: openregister-client
Version: 0.4
Summary: A client for reading data from Registers provided by Government Digital Services
Home-page: https://github.com/ministryofjustice/openregister-client
Author: Ministry of Justice Digital & Technology
Author-email: dev@digital.justice.gov.uk
License: MIT
Keywords: openregister govuk
Platform: UNKNOWN
Classifier: Development Status :: 4 - Beta
Classifier: Intended Audience :: Developers
Classifier: License :: OSI Approved :: MIT License
Classifier: Natural Language :: English
Classifier: Operating System :: OS Independent
Classifier: Programming Language :: Python :: 3
Classifier: Programming Language :: Python :: 3.6
Classifier: Programming Language :: Python :: 3.7
Classifier: Programming Language :: Python :: 3.8
Requires-Dist: requests
Provides-Extra: django
Requires-Dist: django ; extra == 'django'
Provides-Extra: markdown
Requires-Dist: Markdown ; extra == 'markdown'
Provides-Extra: pytz
Requires-Dist: pytz ; extra == 'pytz'
